mkdocs_header_dropdown/__init__.py
mkdocs_header_dropdown/plugin.py
mkdocs_header_dropdown/templates/main.html
mkdocs_header_dropdown/templates/partials/header-dropdown.html
mkdocs_header_dropdown/templates/partials/header.html
mkdocs_header_dropdown-0.3.0.dist-info/licenses/LICENSE
mkdocs_header_dropdown-0.3.0.dist-info/METADATA
mkdocs_header_dropdown-0.3.0.dist-info/WHEEL
mkdocs_header_dropdown-0.3.0.dist-info/entry_points.txt
mkdocs_header_dropdown-0.3.0.dist-info/top_level.txt
mkdocs_header_dropdown-0.3.0.dist-info/RECORD
