Metadata-Version: 2.4
Name: mkdocs-header-dropdown
Version: 0.3.0
Summary: A MkDocs plugin to add configurable dropdown menus to the Material theme header
Author: CMS Common Analysis Tools
Maintainer: CMS Common Analysis Tools
License-Expression: MIT
Project-URL: Homepage, https://github.com/cms-cat/mkdocs-header-dropdown
Project-URL: Repository, https://github.com/cms-cat/mkdocs-header-dropdown
Project-URL: Issues, https://github.com/cms-cat/mkdocs-header-dropdown/issues
Project-URL: Documentation, https://github.com/cms-cat/mkdocs-header-dropdown#readme
Keywords: mkdocs,plugin,dropdown,navigation,material-theme,documentation
Classifier: Development Status :: 3 - Alpha
Classifier: Intended Audience :: Developers
Classifier: Topic :: Documentation
Classifier: Topic :: Text Processing :: Markup :: Markdown
Classifier: Framework :: MkDocs
Classifier: Programming Language :: Python :: 3
Classifier: Programming Language :: Python :: 3.7
Classifier: Programming Language :: Python :: 3.8
Classifier: Programming Language :: Python :: 3.9
Classifier: Programming Language :: Python :: 3.10
Classifier: Programming Language :: Python :: 3.11
Classifier: Programming Language :: Python :: 3.12
Classifier: Operating System :: OS Independent
Requires-Python: >=3.7
License-File: LICENSE
Requires-Dist: mkdocs>=1.4.0
Requires-Dist: pyyaml
Dynamic: license-file
